txt2cql/__init__.py
txt2cql/main.py
txt2cql-0.1.0.dist-info/LICENSE.md
txt2cql-0.1.0.dist-info/METADATA
txt2cql-0.1.0.dist-info/WHEEL
txt2cql-0.1.0.dist-info/entry_points.txt
txt2cql-0.1.0.dist-info/RECORD
