Metadata-Version: 2.1
Name: txt2cql
Version: 0.1.0
Summary: Convert input text into a valid Centreon Query Language request
Home-page: https://github.com/CentreonLabs/txt2cql
License: AGPL-3.0-or-later
Keywords: centreon,LLM
Author: Denis Roussel
Author-email: droussel@centreon.com
Requires-Python: >=3.11,<4.0
Classifier: License :: OSI Approved :: GNU Affero General Public License v3 or later (AGPLv3+)
Classifier: Programming Language :: Python :: 3
Classifier: Programming Language :: Python :: 3.11
Classifier: Programming Language :: Python :: 3.12
Requires-Dist: openai (>=1,<2)
Requires-Dist: pyperclip (>=1,<2)
Requires-Dist: rich (>=13,<14)
Requires-Dist: typer (>=0,<1)
Project-URL: Repository, https://github.com/CentreonLabs/txt2cql
